shiny/__init__.py
shiny/__main__.py
shiny/_app.py
shiny/_autoreload.py
shiny/_connection.py
shiny/_datastructures.py
shiny/_deprecated.py
shiny/_docstring.py
shiny/_error.py
shiny/_fileupload.py
shiny/_hostenv.py
shiny/_launchbrowser.py
shiny/_main.py
shiny/_main_add_test.py
shiny/_main_create.py
shiny/_main_create_custom.py
shiny/_main_utils.py
shiny/_namespaces.py
shiny/_shinyenv.py
shiny/_static.py
shiny/_typing_extensions.py
shiny/_utils.py
shiny/_validation.py
shiny/_version.py
shiny/_versions.py
shiny/html_dependencies.py
shiny/http_staticfiles.py
shiny/input_handler.py
shiny/module.py
shiny/plotutils.py
shiny/py.typed
shiny/quarto.py
shiny/types.py
shiny/api-examples/Module/app-core.py
shiny/api-examples/Progress/app-core.py
shiny/api-examples/Progress/app-express.py
shiny/api-examples/Renderer/app-core.py
shiny/api-examples/Renderer/app-express.py
shiny/api-examples/Renderer/renderers.py
shiny/api-examples/SafeException/app-core.py
shiny/api-examples/SafeException/app-express.py
shiny/api-examples/SilentCancelOutputException/app-core.py
shiny/api-examples/SilentCancelOutputException/app-express.py
shiny/api-examples/SilentException/app-core.py
shiny/api-examples/SilentException/app-express.py
shiny/api-examples/Value/app-core.py
shiny/api-examples/Value/app-express.py
shiny/api-examples/accordion/app-core.py
shiny/api-examples/accordion/app-express.py
shiny/api-examples/accordion_panel/app-core.py
shiny/api-examples/accordion_panel/app-express.py
shiny/api-examples/as_fill_item/app-core.py
shiny/api-examples/as_fill_item/app-express.py
shiny/api-examples/as_fillable_container/app-core.py
shiny/api-examples/as_fillable_container/app-express.py
shiny/api-examples/busy_indicators/app-core.py
shiny/api-examples/busy_indicators/app-express.py
shiny/api-examples/calc/app-core.py
shiny/api-examples/calc/app-express.py
shiny/api-examples/card/app-core.py
shiny/api-examples/card/app-express.py
shiny/api-examples/card_body/app-core.py
shiny-1.2.1.dist-info/LICENSE
shiny-1.2.1.dist-info/METADATA
shiny-1.2.1.dist-info/WHEEL
shiny-1.2.1.dist-info/entry_points.txt
shiny-1.2.1.dist-info/top_level.txt
shiny-1.2.1.dist-info/RECORD
