Metadata-Version: 2.1
Name: shiny
Version: 1.2.1
Summary: A web development framework for Python.
Author-email: Winston Chang <winston@posit.co>
License: MIT
Project-URL: Homepage, https://github.com/posit-dev/py-shiny
Project-URL: Documentation, https://shiny.posit.co/py/
Project-URL: Repository, https://github.com/posit-dev/py-shiny
Project-URL: Bug Tracker, https://github.com/posit-dev/py-shiny/issues
Classifier: Development Status :: 5 - Production/Stable
Classifier: Intended Audience :: Developers
Classifier: License :: OSI Approved :: MIT License
Classifier: Natural Language :: English
Classifier: Programming Language :: Python :: 3.9
Classifier: Programming Language :: Python :: 3.10
Classifier: Programming Language :: Python :: 3.11
Classifier: Programming Language :: Python :: 3.12
Requires-Python: >=3.9
License-File: LICENSE
Requires-Dist: typing-extensions>=4.10.0
Requires-Dist: uvicorn>=0.16.0; platform_system != "Emscripten"
Requires-Dist: starlette
Requires-Dist: websockets>=13.0
Requires-Dist: python-multipart
Requires-Dist: htmltools>=0.6.0
Requires-Dist: click>=8.1.4; platform_system != "Emscripten"
Requires-Dist: markdown-it-py>=1.1.0
Requires-Dist: mdit-py-plugins>=0.3.0
Requires-Dist: linkify-it-py>=1.0
Requires-Dist: appdirs>=1.4.4
Requires-Dist: asgiref>=3.5.2
Requires-Dist: packaging>=20.9
Requires-Dist: watchfiles>=0.18.0; platform_system != "Emscripten"
Requires-Dist: questionary>=2.0.0; platform_system != "Emscripten"
Requires-Dist: prompt-toolkit; platform_system != "Emscripten"
Requires-Dist: python-multipart>=0.0.7; platform_system != "Emscripten"
Requires-Dist: setuptools; python_version >= "3.12"
Requires-Dist: narwhals>=1.10.0
Requires-Dist: orjson>=3.10.7
Provides-Extra: theme
Requires-Dist: libsass>=0.23.0; extra == "theme"
Requires-Dist: brand_yml>=0.1.0; extra == "theme"
Provides-Extra: test
Requires-Dist: pytest>=6.2.4; extra == "test"
Requires-Dist: pytest-asyncio>=0.17.2; extra == "test"
Requires-Dist: pytest-playwright>=0.3.0; extra == "test"
Requires-Dist: playwright>=1.43.0; extra == "test"
Requires-Dist: pytest-xdist; extra == "test"
Requires-Dist: pytest-timeout; extra == "test"
Requires-Dist: pytest-rerunfailures; extra == "test"
Requires-Dist: pytest-cov; extra == "test"
Requires-Dist: coverage; extra == "test"
Requires-Dist: syrupy>=4.7.1; extra == "test"
Requires-Dist: psutil; extra == "test"
Requires-Dist: astropy; extra == "test"
Requires-Dist: suntime; extra == "test"
Requires-Dist: timezonefinder; platform_system != "Windows" and extra == "test"
Requires-Dist: ipyleaflet; extra == "test"
Requires-Dist: shinywidgets; extra == "test"
Requires-Dist: seaborn; extra == "test"
Requires-Dist: plotnine; extra == "test"
Requires-Dist: plotly; extra == "test"
Requires-Dist: duckdb; extra == "test"
Requires-Dist: holoviews; extra == "test"
Requires-Dist: bokeh; extra == "test"
Requires-Dist: xarray; extra == "test"
Requires-Dist: geopandas; extra == "test"
Requires-Dist: geodatasets; extra == "test"
Requires-Dist: missingno; extra == "test"
Requires-Dist: rsconnect-python; extra == "test"
Requires-Dist: scikit-learn; extra == "test"
Requires-Dist: folium; extra == "test"
Requires-Dist: palmerpenguins; extra == "test"
Requires-Dist: faicons; extra == "test"
Requires-Dist: ridgeplot; extra == "test"
Requires-Dist: great_tables; extra == "test"
Requires-Dist: modin[all]; extra == "test"
Requires-Dist: polars; extra == "test"
Requires-Dist: dask[dataframe]; extra == "test"
Requires-Dist: pyarrow; extra == "test"
Requires-Dist: pyarrow-stubs; extra == "test"
Provides-Extra: dev
Requires-Dist: black>=24.0; extra == "dev"
Requires-Dist: flake8>=6.0.0; extra == "dev"
Requires-Dist: flake8-bugbear>=23.2.13; extra == "dev"
Requires-Dist: Flake8-pyproject>=1.2.3; extra == "dev"
Requires-Dist: isort>=5.10.1; extra == "dev"
Requires-Dist: libsass>=0.23.0; extra == "dev"
Requires-Dist: brand_yml>=0.1.0; extra == "dev"
Requires-Dist: pyright>=1.1.383; extra == "dev"
Requires-Dist: pre-commit>=2.15.0; extra == "dev"
Requires-Dist: wheel; extra == "dev"
Requires-Dist: matplotlib; extra == "dev"
Requires-Dist: pandas; extra == "dev"
Requires-Dist: pandas-stubs; extra == "dev"
Requires-Dist: polars; extra == "dev"
Requires-Dist: numpy; extra == "dev"
Requires-Dist: shinyswatch>=0.7.0; extra == "dev"
Requires-Dist: python-dotenv; extra == "dev"
Requires-Dist: anthropic; extra == "dev"
Requires-Dist: google-generativeai; python_version >= "3.9" and extra == "dev"
Requires-Dist: langchain_core; extra == "dev"
Requires-Dist: openai; extra == "dev"
Requires-Dist: ollama; extra == "dev"
Requires-Dist: tokenizers; extra == "dev"
Requires-Dist: aiohttp; extra == "dev"
Requires-Dist: beautifulsoup4; extra == "dev"
Provides-Extra: doc
Requires-Dist: jupyter; extra == "doc"
Requires-Dist: jupyter_client<8.0.0; extra == "doc"
Requires-Dist: tabulate; extra == "doc"
Requires-Dist: shinylive; extra == "doc"
Requires-Dist: pydantic>=2.7.4; extra == "doc"
Requires-Dist: quartodoc>=0.8.1; extra == "doc"
Requires-Dist: griffe>=1.3.2; extra == "doc"
